splatstream/__init__.py
splatstream/_core.cp310-win_amd64.pyd
splatstream/engine.py
splatstream/rendered_image.py
splatstream/renderer.py
splatstream-0.1.4.dist-info/METADATA
splatstream-0.1.4.dist-info/WHEEL
splatstream-0.1.4.dist-info/RECORD
