Metadata-Version: 2.2
Name: splatstream
Version: 0.1.4
Summary: Streamlined 3dgs rendering
Author-Email: Jaesung Park <jaesung.cs@gmail.com>
License: MIT
Project-URL: Homepage, https://github.com/jaesung-cs/splatstream
Requires-Python: >=3.10
Requires-Dist: numpy
